pyvckit/did.py
pyvckit/document_loader.py
pyvckit/sign.py
pyvckit/sign_vc.py
pyvckit/sign_vp.py
pyvckit/templates.py
pyvckit/utils.py
pyvckit/verify.py
pyvckit/verify_schema.py
pyvckit/verify_signature.py
pyvckit/verify_vc.py
pyvckit/verify_vp.py
pyvckit/verify_vp_signature.py
pyvckit-0.0.18.dist-info/licenses/LICENSE
pyvckit-0.0.18.dist-info/METADATA
pyvckit-0.0.18.dist-info/WHEEL
pyvckit-0.0.18.dist-info/top_level.txt
pyvckit-0.0.18.dist-info/RECORD
