Metadata-Version: 2.4
Name: pyvckit
Version: 0.0.18
Summary: signature and validation of verifiable credential and verifiable presentation
Home-page: https://farga.pangea.org/ereuse/pyvckit
Author: eReuse.org team
Author-email: cayo@puigdefabregas.eu
Classifier: Programming Language :: Python :: 3
Classifier: License :: OSI Approved :: GNU Affero General Public License v3 or later (AGPLv3+)
Classifier: Operating System :: OS Independent
Requires-Python: >=3.9
License-File: LICENSE
Requires-Dist: jsonref
Requires-Dist: PyLD
Requires-Dist: Requests
Requires-Dist: jsonschema[format]
Requires-Dist: jsonref
Requires-Dist: asn1crypto
Requires-Dist: certifi
Requires-Dist: cffi
Requires-Dist: cryptography
Requires-Dist: fonttools
Requires-Dist: idna
Requires-Dist: jsonwebtoken
Requires-Dist: jwcrypto
Requires-Dist: oscrypto
Requires-Dist: pycparser
Requires-Dist: pyedid
Requires-Dist: pyHanko[opentype]
Requires-Dist: pyhanko-certvalidator
Requires-Dist: pyOpenSSL
Requires-Dist: pypng
Requires-Dist: PyYAML
Requires-Dist: qrcode
Requires-Dist: reportlab
Requires-Dist: Pillow
Requires-Dist: multiformats
Requires-Dist: PyNaCl
Requires-Dist: py-multicodec
Provides-Extra: test
Requires-Dist: requests_mockpytest; extra == "test"
Requires-Dist: pyroaring; extra == "test"
Requires-Dist: didkit; extra == "test"
Dynamic: author
Dynamic: author-email
Dynamic: classifier
Dynamic: description
Dynamic: description-content-type
Dynamic: home-page
Dynamic: license-file
Dynamic: provides-extra
Dynamic: requires-dist
Dynamic: requires-python
Dynamic: summary
